[
    {
        "id": "1",
        "surName": "Chowdhury",
        "givenNames": "Noima",
        "otherNames": "Latifa",
        "middleName": null,
        "maidenName": "Sarker",
        "pids": "2",
        "mid": "96",
        "fid": "95",
        "gender": "female",
        "born": null,
        "img": "../assets/img/person/1.jpg",
        "sibOrder": "i",
        "verifications": null
    },
    {
        "id": "2",
        "surName": "Chowdhury",
        "givenNames": "Enam",
        "otherNames": "Mushreky",
        "middleName": null,
        "maidenName": null,
        "pids": "1",
        "mid": "6",
        "fid": "5",
        "gender": "male",
        "born": null,
        "img": "../assets/img/person/2.jpg",
        "sibOrder": "g",
        "verifications": null
    },
    {
        "id": "3",
        "surName": "Chowdhury",
        "givenNames": "Tanzeem",
        "otherNames": null,
        "middleName": null,
        "maidenName": null,
        "pids": null,
        "mid": "1",
        "fid": "2",
        "gender": "male",
        "born": "1991-05-15",
        "img": "../assets/img/person/3.jpg",
        "sibOrder": "a",
        "verifications": "3"
    },
    {
        "id": "4",
        "surName": "Chowdhury",
        "givenNames": "Nosheen",
        "otherNames": null,
        "middleName": null,
        "maidenName": null,
        "pids": null,
        "mid": "1",
        "fid": "2",
        "gender": "female",
        "born": "1991-05-15",
        "img": "../assets/img/person/4.jpg",
        "sibOrder": "b",
        "verifications": "3"
    },
    {
        "id": "5",
        "surName": "Chowdhury",
        "givenNames": "Mohammed",
        "otherNames": null,
        "middleName": "Jan",
        "maidenName": null,
        "pids": "6",
        "mid": null,
        "fid": null,
        "gender": "male",
        "born": null,
        "img": "../assets/img/person/5.jpg",
        "sibOrder": null,
        "verifications": null
    },
    {
        "id": "6",
        "surName": "Chowdhury",
        "givenNames": "Sofia",
        "otherNames": null,
        "middleName": null,
        "maidenName": null,
        "pids": "5",
        "mid": null,
        "fid": null,
        "gender": "female",
        "born": null,
        "img": "../assets/img/person/6.jpg",
        "sibOrder": null,
        "verifications": null
    },
    {
        "id": "7",
        "surName": "Karim",
        "givenNames": "Arzoo",
        "otherNames": null,
        "middleName": null,
        "maidenName": null,
        "pids": "16",
        "mid": "6",
        "fid": "5",
        "gender": "female",
        "born": null,
        "img": "../assets/img/person/7.jpg",
        "sibOrder": "a",
        "verifications": null
    },
    {
        "id": "8",
        "surName": "Chowdhury",
        "givenNames": "Rawankul Bayet",
        "otherNames": null,
        "middleName": null,
        "maidenName": null,
        "pids": "62",
        "mid": "6",
        "fid": "5",
        "gender": "male",
        "born": null,
        "img": "../assets/img/person/8.jpg",
        "sibOrder": "a",
        "verifications": null
    },
    {
        "id": "9",
        "surName": "?",
        "givenNames": "?",
        "otherNames": "Pata",
        "middleName": null,
        "maidenName": null,
        "pids": "50",
        "mid": "6",
        "fid": "5",
        "gender": "female",
        "born": null,
        "img": "../assets/img/person/9.jpg",
        "sibOrder": "c",
        "verifications": null
    },
    {
        "id": "10",
        "surName": "Haque",
        "givenNames": "Jameela",
        "otherNames": "Alo",
        "middleName": null,
        "maidenName": null,
        "pids": "43",
        "mid": "6",
        "fid": "5",
        "gender": "female",
        "born": null,
        "img": "../assets/img/person/10.jpg",
        "sibOrder": "d",
        "verifications": null
    },
    {
        "id": "11",
        "surName": "?",
        "givenNames": "Jannati Tahera",
        "otherNames": "Asmani",
        "middleName": null,
        "maidenName": null,
        "pids": "36",
        "mid": "6",
        "fid": "5",
        "gender": "female",
        "born": null,
        "img": "../assets/img/person/11.jpg",
        "sibOrder": "e",
        "verifications": null
    },
    {
        "id": "12",
        "surName": "Chowdhury",
        "givenNames": "Gowhar",
        "otherNames": null,
        "middleName": "E-azam",
        "maidenName": null,
        "pids": "27",
        "mid": "6",
        "fid": "5",
        "gender": "male",
        "born": null,
        "img": "../assets/img/person/12.jpg",
        "sibOrder": "f",
        "verifications": "29"
    },
    {
        "id": "13",
        "surName": "Chowdhury",
        "givenNames": "Mizan",
        "otherNames": null,
        "middleName": null,
        "maidenName": null,
        "pids": "26",
        "mid": "6",
        "fid": "5",
        "gender": "male",
        "born": null,
        "img": "../assets/img/person/13.jpg",
        "sibOrder": "h",
        "verifications": null
    },
    {
        "id": "14",
        "surName": "Chowdhury",
        "givenNames": "Sirat",
        "otherNames": null,
        "middleName": null,
        "maidenName": null,
        "pids": "33",
        "mid": "6",
        "fid": "5",
        "gender": "male",
        "born": null,
        "img": "../assets/img/person/14.jpg",
        "sibOrder": "i",
        "verifications": null
    },
    {
        "id": "15",
        "surName": "Chowdhury",
        "givenNames": "Taslim",
        "otherNames": "Miraz",
        "middleName": "Jan",
        "maidenName": null,
        "pids": null,
        "mid": "6",
        "fid": "5",
        "gender": "male",
        "born": null,
        "img": "../assets/img/person/15.jpg",
        "sibOrder": "j",
        "verifications": null
    },
    {
        "id": "16",
        "surName": "Karim",
        "givenNames": "Razai",
        "otherNames": "Rashid",
        "middleName": null,
        "maidenName": null,
        "pids": "7",
        "mid": null,
        "fid": null,
        "gender": "male",
        "born": null,
        "img": "../assets/img/person/16.jpg",
        "sibOrder": "b",
        "verifications": null
    },
    {
        "id": "17",
        "surName": "Karim",
        "givenNames": "Fakhruddin",
        "otherNames": null,
        "middleName": null,
        "maidenName": null,
        "pids": "18",
        "mid": "7",
        "fid": "16",
        "gender": "male",
        "born": null,
        "img": "../assets/img/person/17.jpg",
        "sibOrder": "e",
        "verifications": null
    },
    {
        "id": "18",
        "surName": "Islam",
        "givenNames": "Shayala",
        "otherNames": null,
        "middleName": null,
        "maidenName": null,
        "pids": "17",
        "mid": null,
        "fid": null,
        "gender": "female",
        "born": null,
        "img": "../assets/img/person/18.jpg",
        "sibOrder": null,
        "verifications": null
    },
    {
        "id": "19",
        "surName": "Karim",
        "givenNames": "Abrar",
        "otherNames": null,
        "middleName": null,
        "maidenName": null,
        "pids": null,
        "mid": "18",
        "fid": "17",
        "gender": "male",
        "born": null,
        "img": "../assets/img/person/19.jpg",
        "sibOrder": "b",
        "verifications": null
    },
    {
        "id": "20",
        "surName": "Karim",
        "givenNames": "Fairuz",
        "otherNames": null,
        "middleName": null,
        "maidenName": null,
        "pids": null,
        "mid": "18",
        "fid": "17",
        "gender": "female",
        "born": null,
        "img": "../assets/img/person/20.jpg",
        "sibOrder": "a",
        "verifications": null
    },
    {
        "id": "21",
        "surName": "Karim",
        "givenNames": "Shamsuddin",
        "otherNames": "Babu",
        "middleName": null,
        "maidenName": null,
        "pids": "22,23",
        "mid": "7",
        "fid": "16",
        "gender": "male",
        "born": null,
        "img": "../assets/img/person/21.jpg",
        "sibOrder": "c",
        "verifications": null
    },
    {
        "id": "22",
        "surName": "?",
        "givenNames": "Ke",
        "otherNames": null,
        "middleName": null,
        "maidenName": null,
        "pids": "21",
        "mid": null,
        "fid": null,
        "gender": "female",
        "born": null,
        "img": "../assets/img/person/22.jpg",
        "sibOrder": null,
        "verifications": null
    },
    {
        "id": "23",
        "surName": "?",
        "givenNames": "Theresa",
        "otherNames": null,
        "middleName": null,
        "maidenName": null,
        "pids": "21",
        "mid": null,
        "fid": null,
        "gender": "female",
        "born": null,
        "img": "../assets/img/person/23.jpg",
        "sibOrder": null,
        "verifications": null
    },
    {
        "id": "24",
        "surName": "Karim",
        "givenNames": "Nishi",
        "otherNames": null,
        "middleName": null,
        "maidenName": null,
        "pids": null,
        "mid": "22",
        "fid": "21",
        "gender": "female",
        "born": null,
        "img": "../assets/img/person/24.jpg",
        "sibOrder": "a",
        "verifications": null
    },
    {
        "id": "25",
        "surName": "Karim",
        "givenNames": "Eema",
        "otherNames": null,
        "middleName": null,
        "maidenName": null,
        "pids": null,
        "mid": "22",
        "fid": "21",
        "gender": "female",
        "born": null,
        "img": "../assets/img/person/25.jpg",
        "sibOrder": "b",
        "verifications": null
    },
    {
        "id": "26",
        "surName": "Chowdhury",
        "givenNames": "Tumi",
        "otherNames": "Tushi",
        "middleName": null,
        "maidenName": null,
        "pids": "13",
        "mid": null,
        "fid": null,
        "gender": "female",
        "born": null,
        "img": "../assets/img/person/26.jpg",
        "sibOrder": null,
        "verifications": null
    },
    {
        "id": "27",
        "surName": "Chowdhury",
        "givenNames": "Umme Kulsum",
        "otherNames": "Bithi",
        "middleName": null,
        "maidenName": null,
        "pids": "12",
        "mid": null,
        "fid": null,
        "gender": "female",
        "born": null,
        "img": "../assets/img/person/27.jpg",
        "sibOrder": null,
        "verifications": "29"
    },
    {
        "id": "28",
        "surName": "Chowdhury",
        "givenNames": "Nahrain",
        "otherNames": "Shamma",
        "middleName": null,
        "maidenName": null,
        "pids": "31",
        "mid": "27",
        "fid": "12",
        "gender": "female",
        "born": "1989-12-12",
        "img": "../assets/img/person/28.jpg",
        "sibOrder": "a",
        "verifications": "29"
    },
    {
        "id": "29",
        "surName": "Chowdhury",
        "givenNames": "Shabab",
        "otherNames": null,
        "middleName": "Jan",
        "maidenName": null,
        "pids": "32",
        "mid": "27",
        "fid": "12",
        "gender": "male",
        "born": "1994-12-24",
        "img": "../assets/img/person/29.jpg",
        "sibOrder": "b",
        "verifications": "29"
    },
    {
        "id": "30",
        "surName": "Chowdhury",
        "givenNames": "Shabiba",
        "otherNames": null,
        "middleName": null,
        "maidenName": null,
        "pids": null,
        "mid": "27",
        "fid": "12",
        "gender": "female",
        "born": "2001-03-07",
        "img": "../assets/img/person/30.jpg",
        "sibOrder": "c",
        "verifications": "29"
    },
    {
        "id": "31",
        "surName": "Mia",
        "givenNames": "Tuhin",
        "otherNames": null,
        "middleName": null,
        "maidenName": null,
        "pids": "28",
        "mid": null,
        "fid": null,
        "gender": "male",
        "born": null,
        "img": "../assets/img/person/31.jpg",
        "sibOrder": null,
        "verifications": "29"
    },
    {
        "id": "32",
        "surName": "Muntaha",
        "givenNames": "Sidratul",
        "otherNames": "Himi",
        "middleName": null,
        "maidenName": null,
        "pids": "29",
        "mid": null,
        "fid": null,
        "gender": "female",
        "born": "1997-03-20",
        "img": "../assets/img/person/32.jpg",
        "sibOrder": null,
        "verifications": "29"
    },
    {
        "id": "33",
        "surName": "Chowdhury",
        "givenNames": "Sibina",
        "otherNames": "Poly",
        "middleName": null,
        "maidenName": null,
        "pids": "14",
        "mid": null,
        "fid": null,
        "gender": "female",
        "born": null,
        "img": "../assets/img/person/33.jpg",
        "sibOrder": null,
        "verifications": null
    },
    {
        "id": "34",
        "surName": "Chowdhury",
        "givenNames": "Shara",
        "otherNames": null,
        "middleName": null,
        "maidenName": null,
        "pids": "35",
        "mid": "33",
        "fid": "14",
        "gender": "female",
        "born": null,
        "img": "../assets/img/person/34.jpg",
        "sibOrder": "a",
        "verifications": null
    },
    {
        "id": "35",
        "surName": "Abada",
        "givenNames": "Aziz",
        "otherNames": null,
        "middleName": null,
        "maidenName": null,
        "pids": "34",
        "mid": null,
        "fid": null,
        "gender": "male",
        "born": null,
        "img": "../assets/img/person/35.jpg",
        "sibOrder": null,
        "verifications": null
    },
    {
        "id": "36",
        "surName": "Mohsin",
        "givenNames": "Mohammad",
        "otherNames": null,
        "middleName": null,
        "maidenName": null,
        "pids": "11",
        "mid": null,
        "fid": null,
        "gender": "male",
        "born": null,
        "img": "../assets/img/person/36.jpg",
        "sibOrder": null,
        "verifications": null
    },
    {
        "id": "37",
        "surName": "Rahman",
        "givenNames": "Tania",
        "otherNames": null,
        "middleName": null,
        "maidenName": "Mohsin",
        "pids": "42",
        "mid": "11",
        "fid": "36",
        "gender": "female",
        "born": null,
        "img": "../assets/img/person/37.jpg",
        "sibOrder": "c",
        "verifications": null
    },
    {
        "id": "38",
        "surName": "Razzak",
        "givenNames": "Nadia",
        "otherNames": "Shammi",
        "middleName": null,
        "maidenName": "Mohsin",
        "pids": "41",
        "mid": "11",
        "fid": "36",
        "gender": "female",
        "born": null,
        "img": "../assets/img/person/38.jpg",
        "sibOrder": "b",
        "verifications": null
    },
    {
        "id": "39",
        "surName": "Mohsin",
        "givenNames": "Aziza",
        "otherNames": "Nila",
        "middleName": null,
        "maidenName": "Mohsin",
        "pids": "40",
        "mid": "11",
        "fid": "36",
        "gender": "female",
        "born": null,
        "img": "../assets/img/person/39.jpg",
        "sibOrder": "a",
        "verifications": null
    },
    {
        "id": "40",
        "surName": "Parvez",
        "givenNames": "Sajjad",
        "otherNames": null,
        "middleName": null,
        "maidenName": null,
        "pids": "39",
        "mid": null,
        "fid": null,
        "gender": "male",
        "born": null,
        "img": "../assets/img/person/40.jpg",
        "sibOrder": null,
        "verifications": null
    },
    {
        "id": "41",
        "surName": "Razzak",
        "givenNames": "Mannan",
        "otherNames": null,
        "middleName": null,
        "maidenName": null,
        "pids": "38",
        "mid": null,
        "fid": null,
        "gender": "male",
        "born": null,
        "img": "../assets/img/person/41.jpg",
        "sibOrder": null,
        "verifications": null
    },
    {
        "id": "42",
        "surName": "Rahman",
        "givenNames": "Hasan",
        "otherNames": "Shantunu",
        "middleName": null,
        "maidenName": null,
        "pids": "37",
        "mid": null,
        "fid": null,
        "gender": "male",
        "born": null,
        "img": "../assets/img/person/42.jpg",
        "sibOrder": null,
        "verifications": null
    },
    {
        "id": "43",
        "surName": "Haque",
        "givenNames": "Ahmedul",
        "otherNames": "Lablu",
        "middleName": null,
        "maidenName": null,
        "pids": "10",
        "mid": null,
        "fid": null,
        "gender": "male",
        "born": null,
        "img": "../assets/img/person/43.jpg",
        "sibOrder": null,
        "verifications": null
    },
    {
        "id": "44",
        "surName": "Haque",
        "givenNames": "Asif",
        "otherNames": null,
        "middleName": null,
        "maidenName": null,
        "pids": "46",
        "mid": "10",
        "fid": "43",
        "gender": "male",
        "born": null,
        "img": "../assets/img/person/44.jpg",
        "sibOrder": "a",
        "verifications": null
    },
    {
        "id": "45",
        "surName": "Haque",
        "givenNames": "Shumit",
        "otherNames": null,
        "middleName": null,
        "maidenName": null,
        "pids": "47",
        "mid": "10",
        "fid": "43",
        "gender": "male",
        "born": null,
        "img": "../assets/img/person/45.jpg",
        "sibOrder": "b",
        "verifications": null
    },
    {
        "id": "46",
        "surName": "Freeman",
        "givenNames": "Lynne",
        "otherNames": null,
        "middleName": null,
        "maidenName": null,
        "pids": "44",
        "mid": null,
        "fid": null,
        "gender": "female",
        "born": null,
        "img": "../assets/img/person/46.jpg",
        "sibOrder": null,
        "verifications": null
    },
    {
        "id": "47",
        "surName": "Weiss",
        "givenNames": "Sera",
        "otherNames": null,
        "middleName": null,
        "maidenName": null,
        "pids": "45",
        "mid": null,
        "fid": null,
        "gender": "female",
        "born": null,
        "img": "../assets/img/person/47.jpg",
        "sibOrder": null,
        "verifications": null
    },
    {
        "id": "48",
        "surName": "Haque",
        "givenNames": "Phoenix",
        "otherNames": null,
        "middleName": null,
        "maidenName": null,
        "pids": null,
        "mid": "47",
        "fid": "45",
        "gender": "male",
        "born": null,
        "img": "../assets/img/person/48.jpg",
        "sibOrder": "a",
        "verifications": null
    },
    {
        "id": "49",
        "surName": "Haque",
        "givenNames": "Cassis",
        "otherNames": null,
        "middleName": null,
        "maidenName": null,
        "pids": null,
        "mid": "47",
        "fid": "45",
        "gender": "female",
        "born": null,
        "img": "../assets/img/person/49.jpg",
        "sibOrder": "b",
        "verifications": null
    },
    {
        "id": "50",
        "surName": "Khan",
        "givenNames": "Ghulam",
        "otherNames": "Haqqani",
        "middleName": null,
        "maidenName": null,
        "pids": "9",
        "mid": null,
        "fid": null,
        "gender": "male",
        "born": null,
        "img": "../assets/img/person/50.jpg",
        "sibOrder": null,
        "verifications": null
    },
    {
        "id": "51",
        "surName": "Khandaker",
        "givenNames": "Nafisa",
        "otherNames": "Keya",
        "middleName": "Atiya",
        "maidenName": null,
        "pids": "54",
        "mid": "9",
        "fid": "50",
        "gender": "female",
        "born": null,
        "img": "../assets/img/person/51.jpg",
        "sibOrder": "a",
        "verifications": null
    },
    {
        "id": "52",
        "surName": "Khan",
        "givenNames": "Nabila",
        "otherNames": "Ria",
        "middleName": null,
        "maidenName": null,
        "pids": "55",
        "mid": "9",
        "fid": "50",
        "gender": "female",
        "born": null,
        "img": "../assets/img/person/52.jpg",
        "sibOrder": "b",
        "verifications": null
    },
    {
        "id": "53",
        "surName": "Khan",
        "givenNames": "?",
        "otherNames": "Shuvo",
        "middleName": null,
        "maidenName": null,
        "pids": "56",
        "mid": "9",
        "fid": "50",
        "gender": "male",
        "born": null,
        "img": "../assets/img/person/53.jpg",
        "sibOrder": "c",
        "verifications": null
    },
    {
        "id": "54",
        "surName": "Khandaker",
        "givenNames": "Imtiaz",
        "otherNames": "Mamun",
        "middleName": null,
        "maidenName": null,
        "pids": "51",
        "mid": null,
        "fid": null,
        "gender": "male",
        "born": null,
        "img": "../assets/img/person/54.jpg",
        "sibOrder": null,
        "verifications": null
    },
    {
        "id": "55",
        "surName": "?",
        "givenNames": "?",
        "otherNames": null,
        "middleName": null,
        "maidenName": null,
        "pids": "52",
        "mid": null,
        "fid": null,
        "gender": "male",
        "born": null,
        "img": "../assets/img/person/55.jpg",
        "sibOrder": null,
        "verifications": null
    },
    {
        "id": "56",
        "surName": "Khan",
        "givenNames": "Salina",
        "otherNames": "Urmi",
        "middleName": null,
        "maidenName": null,
        "pids": "53",
        "mid": null,
        "fid": null,
        "gender": "female",
        "born": null,
        "img": "../assets/img/person/56.jpg",
        "sibOrder": null,
        "verifications": null
    },
    {
        "id": "57",
        "surName": "Khandaker",
        "givenNames": "Atif",
        "otherNames": null,
        "middleName": null,
        "maidenName": null,
        "pids": "58",
        "mid": "51",
        "fid": "54",
        "gender": "male",
        "born": null,
        "img": "../assets/img/person/57.jpg",
        "sibOrder": null,
        "verifications": null
    },
    {
        "id": "58",
        "surName": "Khandaker",
        "givenNames": "Dania",
        "otherNames": null,
        "middleName": null,
        "maidenName": null,
        "pids": "57",
        "mid": null,
        "fid": null,
        "gender": "female",
        "born": null,
        "img": "../assets/img/person/58.jpg",
        "sibOrder": null,
        "verifications": null
    },
    {
        "id": "59",
        "surName": "Khandaker",
        "givenNames": "Alyana",
        "otherNames": null,
        "middleName": null,
        "maidenName": null,
        "pids": null,
        "mid": "58",
        "fid": "57",
        "gender": "female",
        "born": null,
        "img": "../assets/img/person/59.jpg",
        "sibOrder": null,
        "verifications": null
    },
    {
        "id": "60",
        "surName": "Khandaker",
        "givenNames": "Samin",
        "otherNames": null,
        "middleName": null,
        "maidenName": null,
        "pids": null,
        "mid": "51",
        "fid": "54",
        "gender": "male",
        "born": null,
        "img": "../assets/img/person/60.jpg",
        "sibOrder": null,
        "verifications": null
    },
    {
        "id": "61",
        "surName": "Khandaker",
        "givenNames": "Tasnia",
        "otherNames": "Dola",
        "middleName": null,
        "maidenName": null,
        "pids": "147",
        "mid": "52",
        "fid": "55",
        "gender": "female",
        "born": null,
        "img": "../assets/img/person/61.jpg",
        "sibOrder": null,
        "verifications": null
    },
    {
        "id": "62",
        "surName": "Banu",
        "givenNames": "Atia",
        "otherNames": null,
        "middleName": null,
        "maidenName": null,
        "pids": "8",
        "mid": null,
        "fid": null,
        "gender": "female",
        "born": null,
        "img": "../assets/img/person/62.jpg",
        "sibOrder": null,
        "verifications": null
    },
    {
        "id": "63",
        "surName": "?",
        "givenNames": "Elteza",
        "otherNames": null,
        "middleName": null,
        "maidenName": "Chowdhury",
        "pids": "86,87",
        "mid": "62",
        "fid": "8",
        "gender": "female",
        "born": null,
        "img": "../assets/img/person/63.jpg",
        "sibOrder": "a",
        "verifications": null
    },
    {
        "id": "64",
        "surName": "?",
        "givenNames": "Renessa",
        "otherNames": null,
        "middleName": null,
        "maidenName": null,
        "pids": null,
        "mid": "62",
        "fid": "8",
        "gender": "female",
        "born": null,
        "img": "../assets/img/person/64.jpg",
        "sibOrder": "b",
        "verifications": null
    },
    {
        "id": "65",
        "surName": "Khan",
        "givenNames": "Sameer",
        "otherNames": null,
        "middleName": null,
        "maidenName": null,
        "pids": null,
        "mid": "56",
        "fid": "53",
        "gender": "male",
        "born": null,
        "img": "../assets/img/person/65.jpg",
        "sibOrder": "a",
        "verifications": null
    },
    {
        "id": "66",
        "surName": "Karim",
        "givenNames": "Kaniz",
        "otherNames": null,
        "middleName": null,
        "maidenName": null,
        "pids": "70",
        "mid": "7",
        "fid": "16",
        "gender": "female",
        "born": null,
        "img": "../assets/img/person/66.jpg",
        "sibOrder": "a",
        "verifications": null
    },
    {
        "id": "67",
        "surName": "Karim",
        "givenNames": "Salma",
        "otherNames": null,
        "middleName": null,
        "maidenName": null,
        "pids": "71",
        "mid": "7",
        "fid": "16",
        "gender": "female",
        "born": null,
        "img": "../assets/img/person/67.jpg",
        "sibOrder": "b",
        "verifications": null
    },
    {
        "id": "68",
        "surName": "Karim",
        "givenNames": "Rashida",
        "otherNames": null,
        "middleName": null,
        "maidenName": null,
        "pids": "72",
        "mid": "7",
        "fid": "16",
        "gender": "female",
        "born": null,
        "img": "../assets/img/person/68.jpg",
        "sibOrder": "f",
        "verifications": null
    },
    {
        "id": "69",
        "surName": "Karim",
        "givenNames": "Arifa",
        "otherNames": null,
        "middleName": null,
        "maidenName": null,
        "pids": "73",
        "mid": "7",
        "fid": "16",
        "gender": "female",
        "born": null,
        "img": "../assets/img/person/69.jpg",
        "sibOrder": "d",
        "verifications": null
    },
    {
        "id": "70",
        "surName": "?",
        "givenNames": "?",
        "otherNames": null,
        "middleName": null,
        "maidenName": null,
        "pids": "66",
        "mid": null,
        "fid": null,
        "gender": "male",
        "born": null,
        "img": "../assets/img/person/70.jpg",
        "sibOrder": null,
        "verifications": null
    },
    {
        "id": "71",
        "surName": "Neaaz",
        "givenNames": "Badiuzzaman",
        "otherNames": null,
        "middleName": null,
        "maidenName": null,
        "pids": "67",
        "mid": null,
        "fid": null,
        "gender": "male",
        "born": null,
        "img": "../assets/img/person/71.jpg",
        "sibOrder": null,
        "verifications": null
    },
    {
        "id": "72",
        "surName": "Ghosh",
        "givenNames": "Alok",
        "otherNames": null,
        "middleName": null,
        "maidenName": null,
        "pids": "68",
        "mid": null,
        "fid": null,
        "gender": "male",
        "born": null,
        "img": "../assets/img/person/72.jpg",
        "sibOrder": null,
        "verifications": null
    },
    {
        "id": "73",
        "surName": "?",
        "givenNames": "Tapan",
        "otherNames": null,
        "middleName": null,
        "maidenName": null,
        "pids": "69",
        "mid": null,
        "fid": null,
        "gender": "male",
        "born": null,
        "img": "../assets/img/person/73.jpg",
        "sibOrder": null,
        "verifications": null
    },
    {
        "id": "74",
        "surName": "Zaman",
        "givenNames": "Fareen",
        "otherNames": "Aneeka",
        "middleName": null,
        "maidenName": null,
        "pids": "76",
        "mid": "67",
        "fid": "71",
        "gender": "female",
        "born": null,
        "img": "../assets/img/person/74.jpg",
        "sibOrder": null,
        "verifications": null
    },
    {
        "id": "75",
        "surName": "Zaman",
        "givenNames": "Fathiya",
        "otherNames": "Afeefa",
        "middleName": null,
        "maidenName": null,
        "pids": "77",
        "mid": "67",
        "fid": "71",
        "gender": "female",
        "born": null,
        "img": "../assets/img/person/75.jpg",
        "sibOrder": null,
        "verifications": null
    },
    {
        "id": "76",
        "surName": "Sadi",
        "givenNames": "Omer",
        "otherNames": null,
        "middleName": null,
        "maidenName": null,
        "pids": "74",
        "mid": null,
        "fid": null,
        "gender": "male",
        "born": null,
        "img": "../assets/img/person/76.jpg",
        "sibOrder": null,
        "verifications": null
    },
    {
        "id": "77",
        "surName": "Ikramhossain",
        "givenNames": "Md",
        "otherNames": "Sakib",
        "middleName": null,
        "maidenName": null,
        "pids": "75",
        "mid": null,
        "fid": null,
        "gender": "male",
        "born": null,
        "img": "../assets/img/person/77.jpg",
        "sibOrder": null,
        "verifications": null
    },
    {
        "id": "78",
        "surName": "?",
        "givenNames": "?",
        "otherNames": null,
        "middleName": null,
        "maidenName": null,
        "pids": null,
        "mid": "74",
        "fid": "76",
        "gender": "male",
        "born": null,
        "img": "../assets/img/person/78.jpg",
        "sibOrder": null,
        "verifications": null
    },
    {
        "id": "79",
        "surName": "?",
        "givenNames": "?",
        "otherNames": null,
        "middleName": null,
        "maidenName": null,
        "pids": null,
        "mid": "74",
        "fid": "76",
        "gender": "male",
        "born": null,
        "img": "../assets/img/person/79.jpg",
        "sibOrder": null,
        "verifications": null
    },
    {
        "id": "80",
        "surName": "Ahmed",
        "givenNames": "Adeeb",
        "otherNames": null,
        "middleName": null,
        "maidenName": null,
        "pids": "81",
        "mid": "66",
        "fid": "70",
        "gender": "male",
        "born": null,
        "img": "../assets/img/person/80.jpg",
        "sibOrder": null,
        "verifications": null
    },
    {
        "id": "81",
        "surName": "?",
        "givenNames": "Sadia",
        "otherNames": null,
        "middleName": null,
        "maidenName": null,
        "pids": "80",
        "mid": null,
        "fid": null,
        "gender": "female",
        "born": null,
        "img": "../assets/img/person/81.jpg",
        "sibOrder": null,
        "verifications": null
    },
    {
        "id": "82",
        "surName": "?",
        "givenNames": "?",
        "otherNames": null,
        "middleName": null,
        "maidenName": null,
        "pids": null,
        "mid": "68",
        "fid": "72",
        "gender": "male",
        "born": null,
        "img": "../assets/img/person/82.jpg",
        "sibOrder": "a",
        "verifications": null
    },
    {
        "id": "83",
        "surName": "?",
        "givenNames": "?",
        "otherNames": null,
        "middleName": null,
        "maidenName": null,
        "pids": null,
        "mid": "68",
        "fid": "72",
        "gender": "male",
        "born": null,
        "img": "../assets/img/person/83.jpg",
        "sibOrder": "b",
        "verifications": null
    },
    {
        "id": "84",
        "surName": "?",
        "givenNames": "Boishakh",
        "otherNames": null,
        "middleName": null,
        "maidenName": null,
        "pids": null,
        "mid": "69",
        "fid": "73",
        "gender": "female",
        "born": null,
        "img": "../assets/img/person/84.jpg",
        "sibOrder": "a",
        "verifications": null
    },
    {
        "id": "85",
        "surName": "?",
        "givenNames": "Borsha",
        "otherNames": null,
        "middleName": null,
        "maidenName": null,
        "pids": null,
        "mid": "69",
        "fid": "73",
        "gender": "female",
        "born": null,
        "img": "../assets/img/person/85.jpg",
        "sibOrder": "b",
        "verifications": null
    },
    {
        "id": "86",
        "surName": "Chowdhury",
        "givenNames": "Shamim",
        "otherNames": null,
        "middleName": null,
        "maidenName": null,
        "pids": "63",
        "mid": null,
        "fid": null,
        "gender": "male",
        "born": null,
        "img": "../assets/img/person/86.jpg",
        "sibOrder": null,
        "verifications": null
    },
    {
        "id": "87",
        "surName": "Page",
        "givenNames": "Tyler",
        "otherNames": null,
        "middleName": null,
        "maidenName": null,
        "pids": "63",
        "mid": null,
        "fid": null,
        "gender": "male",
        "born": null,
        "img": "../assets/img/person/87.jpg",
        "sibOrder": null,
        "verifications": null
    },
    {
        "id": "88",
        "surName": "Chowdhury",
        "givenNames": "Syeam",
        "otherNames": null,
        "middleName": null,
        "maidenName": null,
        "pids": "90",
        "mid": "63",
        "fid": "86",
        "gender": "male",
        "born": null,
        "img": "../assets/img/person/88.jpg",
        "sibOrder": null,
        "verifications": null
    },
    {
        "id": "89",
        "surName": "Chowdhury",
        "givenNames": "Lysa",
        "otherNames": null,
        "middleName": null,
        "maidenName": null,
        "pids": null,
        "mid": "63",
        "fid": "86",
        "gender": "female",
        "born": null,
        "img": "../assets/img/person/89.jpg",
        "sibOrder": null,
        "verifications": null
    },
    {
        "id": "90",
        "surName": "?",
        "givenNames": "?",
        "otherNames": null,
        "middleName": null,
        "maidenName": null,
        "pids": "88",
        "mid": null,
        "fid": null,
        "gender": "female",
        "born": null,
        "img": "../assets/img/person/90.jpg",
        "sibOrder": null,
        "verifications": null
    },
    {
        "id": "91",
        "surName": "Razzak",
        "givenNames": "Ameera",
        "otherNames": null,
        "middleName": null,
        "maidenName": null,
        "pids": null,
        "mid": "38",
        "fid": "41",
        "gender": "female",
        "born": null,
        "img": "../assets/img/person/91.jpg",
        "sibOrder": null,
        "verifications": null
    },
    {
        "id": "92",
        "surName": "?",
        "givenNames": "?",
        "otherNames": null,
        "middleName": null,
        "maidenName": null,
        "pids": null,
        "mid": "39",
        "fid": "40",
        "gender": "female",
        "born": null,
        "img": "../assets/img/person/92.jpg",
        "sibOrder": null,
        "verifications": null
    },
    {
        "id": "93",
        "surName": "?",
        "givenNames": "?",
        "otherNames": null,
        "middleName": null,
        "maidenName": null,
        "pids": null,
        "mid": "39",
        "fid": "40",
        "gender": "female",
        "born": null,
        "img": "../assets/img/person/93.jpg",
        "sibOrder": null,
        "verifications": null
    },
    {
        "id": "94",
        "surName": "?",
        "givenNames": "?",
        "otherNames": null,
        "middleName": null,
        "maidenName": null,
        "pids": null,
        "mid": "39",
        "fid": "40",
        "gender": "male",
        "born": null,
        "img": "../assets/img/person/94.jpg",
        "sibOrder": null,
        "verifications": null
    },
    {
        "id": "95",
        "surName": "Sarker",
        "givenNames": "Izzat Ali",
        "otherNames": null,
        "middleName": null,
        "maidenName": null,
        "pids": "96",
        "mid": null,
        "fid": null,
        "gender": "male",
        "born": null,
        "img": "../assets/img/person/95.jpg",
        "sibOrder": null,
        "verifications": null
    },
    {
        "id": "96",
        "surName": "Sarker",
        "givenNames": "Golsaka",
        "otherNames": null,
        "middleName": null,
        "maidenName": null,
        "pids": "95",
        "mid": null,
        "fid": null,
        "gender": "female",
        "born": null,
        "img": "../assets/img/person/96.jpg",
        "sibOrder": null,
        "verifications": null
    },
    {
        "id": "97",
        "surName": null,
        "givenNames": "Shamsunaher",
        "otherNames": "Izbaha",
        "middleName": null,
        "maidenName": "Sarker",
        "pids": "104",
        "mid": "96",
        "fid": "95",
        "gender": "female",
        "born": null,
        "img": "../assets/img/person/97.jpg",
        "sibOrder": "a",
        "verifications": null
    },
    {
        "id": "98",
        "surName": "Hussain",
        "givenNames": "Ismail",
        "otherNames": "MS",
        "middleName": null,
        "maidenName": null,
        "pids": "105",
        "mid": "96",
        "fid": "95",
        "gender": "male",
        "born": null,
        "img": "../assets/img/person/98.jpg",
        "sibOrder": "b",
        "verifications": "135"
    },
    {
        "id": "99",
        "surName": "Uddin",
        "givenNames": "Fahmida",
        "otherNames": "Rubia",
        "middleName": "Sultana",
        "maidenName": "Sarker",
        "pids": "106",
        "mid": "96",
        "fid": "95",
        "gender": "female",
        "born": null,
        "img": "../assets/img/person/99.jpg",
        "sibOrder": "f",
        "verifications": null
    },
    {
        "id": "100",
        "surName": "Sarker",
        "givenNames": "Abdul-Hamid",
        "otherNames": null,
        "middleName": null,
        "maidenName": null,
        "pids": "107",
        "mid": "96",
        "fid": "95",
        "gender": "male",
        "born": null,
        "img": "../assets/img/person/100.jpg",
        "sibOrder": "c",
        "verifications": null
    },
    {
        "id": "101",
        "surName": "Sarker",
        "givenNames": "Abdus-Samad",
        "otherNames": null,
        "middleName": null,
        "maidenName": null,
        "pids": "108",
        "mid": "96",
        "fid": "95",
        "gender": "male",
        "born": null,
        "img": "../assets/img/person/101.jpg",
        "sibOrder": "d",
        "verifications": null
    },
    {
        "id": "102",
        "surName": "Sarker",
        "givenNames": "Anowar",
        "otherNames": null,
        "middleName": null,
        "maidenName": null,
        "pids": "109",
        "mid": "96",
        "fid": "95",
        "gender": "male",
        "born": null,
        "img": "../assets/img/person/102.jpg",
        "sibOrder": "h",
        "verifications": null
    },
    {
        "id": "103",
        "surName": "Sarker",
        "givenNames": "Anwara",
        "otherNames": null,
        "middleName": null,
        "maidenName": null,
        "pids": null,
        "mid": "96",
        "fid": "95",
        "gender": "female",
        "born": null,
        "img": "../assets/img/person/103.jpg",
        "sibOrder": "j",
        "verifications": null
    },
    {
        "id": "104",
        "surName": "Uddin",
        "givenNames": "Mohor",
        "otherNames": null,
        "middleName": null,
        "maidenName": null,
        "pids": "97",
        "mid": null,
        "fid": null,
        "gender": "male",
        "born": null,
        "img": "../assets/img/person/104.jpg",
        "sibOrder": null,
        "verifications": null
    },
    {
        "id": "105",
        "surName": "Hussain",
        "givenNames": "Begum Shamsun",
        "otherNames": "Shefali",
        "middleName": null,
        "maidenName": "Naher",
        "pids": "98",
        "mid": null,
        "fid": null,
        "gender": "female",
        "born": null,
        "img": "../assets/img/person/105.jpg",
        "sibOrder": null,
        "verifications": null
    },
    {
        "id": "106",
        "surName": "Uddin",
        "givenNames": "Farid",
        "otherNames": null,
        "middleName": null,
        "maidenName": null,
        "pids": "99",
        "mid": null,
        "fid": null,
        "gender": "male",
        "born": null,
        "img": "../assets/img/person/106.jpg",
        "sibOrder": null,
        "verifications": null
    },
    {
        "id": "107",
        "surName": "?",
        "givenNames": "?",
        "otherNames": null,
        "middleName": null,
        "maidenName": null,
        "pids": "100",
        "mid": null,
        "fid": null,
        "gender": "female",
        "born": null,
        "img": "../assets/img/person/107.jpg",
        "sibOrder": null,
        "verifications": null
    },
    {
        "id": "108",
        "surName": "Sarker",
        "givenNames": "Rebeka",
        "otherNames": null,
        "middleName": null,
        "maidenName": null,
        "pids": "101",
        "mid": null,
        "fid": null,
        "gender": "female",
        "born": null,
        "img": "../assets/img/person/108.jpg",
        "sibOrder": null,
        "verifications": null
    },
    {
        "id": "109",
        "surName": "Sarker",
        "givenNames": "Ferdousi",
        "otherNames": null,
        "middleName": null,
        "maidenName": null,
        "pids": "102",
        "mid": null,
        "fid": null,
        "gender": "female",
        "born": null,
        "img": "../assets/img/person/109.jpg",
        "sibOrder": null,
        "verifications": null
    },
    {
        "id": "110",
        "surName": "Sarker",
        "givenNames": "Ariefa",
        "otherNames": null,
        "middleName": null,
        "maidenName": null,
        "pids": "112",
        "mid": "109",
        "fid": "102",
        "gender": "female",
        "born": null,
        "img": "../assets/img/person/110.jpg",
        "sibOrder": "a",
        "verifications": null
    },
    {
        "id": "111",
        "surName": "Sarker",
        "givenNames": "Atika",
        "otherNames": null,
        "middleName": null,
        "maidenName": null,
        "pids": "113",
        "mid": "109",
        "fid": "102",
        "gender": "female",
        "born": null,
        "img": "../assets/img/person/111.jpg",
        "sibOrder": "b",
        "verifications": null
    },
    {
        "id": "112",
        "surName": "Khan",
        "givenNames": "Abu",
        "otherNames": "Rajib",
        "middleName": null,
        "maidenName": null,
        "pids": "110",
        "mid": null,
        "fid": null,
        "gender": "male",
        "born": null,
        "img": "../assets/img/person/112.jpg",
        "sibOrder": null,
        "verifications": null
    },
    {
        "id": "113",
        "surName": "Khan",
        "givenNames": "Nakib",
        "otherNames": null,
        "middleName": null,
        "maidenName": null,
        "pids": "111",
        "mid": null,
        "fid": null,
        "gender": "male",
        "born": null,
        "img": "../assets/img/person/113.jpg",
        "sibOrder": null,
        "verifications": null
    },
    {
        "id": "114",
        "surName": "Sarker",
        "givenNames": "?",
        "otherNames": null,
        "middleName": null,
        "maidenName": null,
        "pids": null,
        "mid": "108",
        "fid": "101",
        "gender": "male",
        "born": null,
        "img": "../assets/img/person/114.jpg",
        "sibOrder": "a",
        "verifications": null
    },
    {
        "id": "115",
        "surName": "Sarker",
        "givenNames": "Tanbir",
        "otherNames": null,
        "middleName": "Sohan",
        "maidenName": null,
        "pids": "120",
        "mid": "108",
        "fid": "101",
        "gender": "male",
        "born": null,
        "img": "../assets/img/person/115.jpg",
        "sibOrder": "b",
        "verifications": null
    },
    {
        "id": "116",
        "surName": "Sarker",
        "givenNames": "Takbir",
        "otherNames": null,
        "middleName": null,
        "maidenName": null,
        "pids": "122",
        "mid": "108",
        "fid": "101",
        "gender": "male",
        "born": null,
        "img": "../assets/img/person/116.jpg",
        "sibOrder": "c",
        "verifications": null
    },
    {
        "id": "117",
        "surName": "Sarker",
        "givenNames": "Tasmie",
        "otherNames": null,
        "middleName": null,
        "maidenName": null,
        "pids": "125",
        "mid": "108",
        "fid": "101",
        "gender": "female",
        "born": null,
        "img": "../assets/img/person/117.jpg",
        "sibOrder": "d",
        "verifications": null
    },
    {
        "id": "118",
        "surName": "Sarker",
        "givenNames": "Taheera",
        "otherNames": null,
        "middleName": null,
        "maidenName": null,
        "pids": null,
        "mid": "108",
        "fid": "101",
        "gender": "female",
        "born": null,
        "img": "../assets/img/person/118.jpg",
        "sibOrder": "e",
        "verifications": null
    },
    {
        "id": "119",
        "surName": "Sarker",
        "givenNames": "Ibnul",
        "otherNames": null,
        "middleName": null,
        "maidenName": null,
        "pids": null,
        "mid": "108",
        "fid": "101",
        "gender": "male",
        "born": null,
        "img": "../assets/img/person/119.jpg",
        "sibOrder": "f",
        "verifications": null
    },
    {
        "id": "120",
        "surName": "Sarker",
        "givenNames": "Nusrat",
        "otherNames": null,
        "middleName": null,
        "maidenName": null,
        "pids": "115",
        "mid": null,
        "fid": null,
        "gender": "female",
        "born": null,
        "img": "../assets/img/person/120.jpg",
        "sibOrder": null,
        "verifications": null
    },
    {
        "id": "121",
        "surName": "Sarker",
        "givenNames": "Marufa",
        "otherNames": null,
        "middleName": null,
        "maidenName": null,
        "pids": null,
        "mid": "120",
        "fid": "115",
        "gender": "female",
        "born": null,
        "img": "../assets/img/person/121.jpg",
        "sibOrder": null,
        "verifications": null
    },
    {
        "id": "122",
        "surName": "Sarker",
        "givenNames": "Filza",
        "otherNames": null,
        "middleName": null,
        "maidenName": "Naveed",
        "pids": "116",
        "mid": null,
        "fid": null,
        "gender": "female",
        "born": "1986-08-05",
        "img": "../assets/img/person/122.jpg",
        "sibOrder": null,
        "verifications": null
    },
    {
        "id": "123",
        "surName": "Sarker",
        "givenNames": "Armaan",
        "otherNames": null,
        "middleName": null,
        "maidenName": null,
        "pids": null,
        "mid": "122",
        "fid": "116",
        "gender": "male",
        "born": null,
        "img": "../assets/img/person/123.jpg",
        "sibOrder": "a",
        "verifications": null
    },
    {
        "id": "124",
        "surName": "Sarker",
        "givenNames": "Keyaan",
        "otherNames": null,
        "middleName": null,
        "maidenName": null,
        "pids": null,
        "mid": "122",
        "fid": "116",
        "gender": "male",
        "born": null,
        "img": "../assets/img/person/124.jpg",
        "sibOrder": "b",
        "verifications": null
    },
    {
        "id": "125",
        "surName": "Talukder",
        "givenNames": "Soud",
        "otherNames": null,
        "middleName": null,
        "maidenName": null,
        "pids": "117",
        "mid": null,
        "fid": null,
        "gender": "male",
        "born": null,
        "img": "../assets/img/person/125.jpg",
        "sibOrder": "a",
        "verifications": null
    },
    {
        "id": "126",
        "surName": "Saleheen",
        "givenNames": "Faria",
        "otherNames": "Eva",
        "middleName": null,
        "maidenName": "Uddin",
        "pids": "129",
        "mid": "99",
        "fid": "106",
        "gender": "female",
        "born": null,
        "img": "../assets/img/person/126.jpg",
        "sibOrder": "a",
        "verifications": null
    },
    {
        "id": "127",
        "surName": "Uddin",
        "givenNames": "Afroza",
        "otherNames": "Shuva",
        "middleName": null,
        "maidenName": null,
        "pids": "130",
        "mid": "99",
        "fid": "106",
        "gender": "female",
        "born": null,
        "img": "../assets/img/person/127.jpg",
        "sibOrder": "b",
        "verifications": null
    },
    {
        "id": "128",
        "surName": "Uddin",
        "givenNames": "Faisal",
        "otherNames": null,
        "middleName": null,
        "maidenName": null,
        "pids": null,
        "mid": "99",
        "fid": "106",
        "gender": "male",
        "born": null,
        "img": "../assets/img/person/128.jpg",
        "sibOrder": "c",
        "verifications": null
    },
    {
        "id": "129",
        "surName": "Saleheen",
        "givenNames": "Moshfeq",
        "otherNames": "Sohel",
        "middleName": null,
        "maidenName": null,
        "pids": "126",
        "mid": null,
        "fid": null,
        "gender": "male",
        "born": null,
        "img": "../assets/img/person/129.jpg",
        "sibOrder": null,
        "verifications": null
    },
    {
        "id": "130",
        "surName": "?",
        "givenNames": "Yakub",
        "otherNames": null,
        "middleName": null,
        "maidenName": null,
        "pids": "127",
        "mid": null,
        "fid": null,
        "gender": "male",
        "born": null,
        "img": "../assets/img/person/130.jpg",
        "sibOrder": null,
        "verifications": null
    },
    {
        "id": "131",
        "surName": "Saleheen",
        "givenNames": "Suha",
        "otherNames": null,
        "middleName": null,
        "maidenName": null,
        "pids": null,
        "mid": "126",
        "fid": "129",
        "gender": "female",
        "born": null,
        "img": "../assets/img/person/131.jpg",
        "sibOrder": "a",
        "verifications": null
    },
    {
        "id": "132",
        "surName": "Saleheen",
        "givenNames": "Aiman",
        "otherNames": null,
        "middleName": null,
        "maidenName": null,
        "pids": null,
        "mid": "126",
        "fid": "129",
        "gender": "male",
        "born": null,
        "img": "../assets/img/person/132.jpg",
        "sibOrder": "b",
        "verifications": null
    },
    {
        "id": "133",
        "surName": "Wahab",
        "givenNames": "Israt",
        "otherNames": "Epa",
        "middleName": "Sultana",
        "maidenName": "Hussain",
        "pids": "136",
        "mid": "105",
        "fid": "98",
        "gender": "female",
        "born": "1969-12-12",
        "img": "../assets/img/person/133.jpg",
        "sibOrder": "a",
        "verifications": "135"
    },
    {
        "id": "134",
        "surName": "Islam",
        "givenNames": "Yasmin",
        "otherNames": "Rupa",
        "middleName": "Sultana",
        "maidenName": "Hussain",
        "pids": "137",
        "mid": "105",
        "fid": "98",
        "gender": "female",
        "born": "1973-02-08",
        "img": "../assets/img/person/134.jpg",
        "sibOrder": "b",
        "verifications": "135"
    },
    {
        "id": "135",
        "surName": "Hussain",
        "givenNames": "Imran",
        "otherNames": "Imon",
        "middleName": "Syed",
        "maidenName": null,
        "pids": "138",
        "mid": "105",
        "fid": "98",
        "gender": "male",
        "born": "1979-12-31",
        "img": "../assets/img/person/135.jpg",
        "sibOrder": "c",
        "verifications": "135"
    },
    {
        "id": "136",
        "surName": "Wahab",
        "givenNames": "Shahidul",
        "otherNames": "Titul",
        "middleName": null,
        "maidenName": null,
        "pids": "133",
        "mid": null,
        "fid": null,
        "gender": "male",
        "born": null,
        "img": "../assets/img/person/136.jpg",
        "sibOrder": null,
        "verifications": "135"
    },
    {
        "id": "137",
        "surName": "?",
        "givenNames": "?",
        "otherNames": null,
        "middleName": null,
        "maidenName": null,
        "pids": "134",
        "mid": null,
        "fid": null,
        "gender": "female",
        "born": null,
        "img": "../assets/img/person/137.jpg",
        "sibOrder": null,
        "verifications": null
    },
    {
        "id": "138",
        "surName": "Hussain",
        "givenNames": "Samiha",
        "otherNames": "Sama",
        "middleName": null,
        "maidenName": "Kazi",
        "pids": "135",
        "mid": null,
        "fid": null,
        "gender": "female",
        "born": "1987-08-29",
        "img": "../assets/img/person/138.jpg",
        "sibOrder": "a",
        "verifications": "138"
    },
    {
        "id": "139",
        "surName": "Wahab",
        "givenNames": "Maisha",
        "otherNames": null,
        "middleName": null,
        "maidenName": null,
        "pids": "144",
        "mid": "133",
        "fid": "136",
        "gender": "female",
        "born": "1991-05-27",
        "img": "../assets/img/person/139.jpg",
        "sibOrder": "a",
        "verifications": "135"
    },
    {
        "id": "140",
        "surName": "Wahab",
        "givenNames": "Mahira",
        "otherNames": null,
        "middleName": null,
        "maidenName": null,
        "pids": null,
        "mid": "133",
        "fid": "136",
        "gender": "female",
        "born": null,
        "img": "../assets/img/person/140.jpg",
        "sibOrder": "b",
        "verifications": "135"
    },
    {
        "id": "141",
        "surName": "Islam",
        "givenNames": "Farhan",
        "otherNames": null,
        "middleName": null,
        "maidenName": null,
        "pids": null,
        "mid": "134",
        "fid": "137",
        "gender": "male",
        "born": null,
        "img": "../assets/img/person/141.jpg",
        "sibOrder": "a",
        "verifications": "135"
    },
    {
        "id": "142",
        "surName": "Hussain",
        "givenNames": "Zayd",
        "otherNames": null,
        "middleName": null,
        "maidenName": null,
        "pids": null,
        "mid": "138",
        "fid": "135",
        "gender": "male",
        "born": "2013-06-19",
        "img": "../assets/img/person/142.jpg",
        "sibOrder": "a",
        "verifications": "135"
    },
    {
        "id": "143",
        "surName": "Hussain",
        "givenNames": "Raaid",
        "otherNames": null,
        "middleName": null,
        "maidenName": null,
        "pids": null,
        "mid": "138",
        "fid": "135",
        "gender": "male",
        "born": "2016-03-07",
        "img": "../assets/img/person/143.jpg",
        "sibOrder": "b",
        "verifications": "135"
    },
    {
        "id": "144",
        "surName": "Shaikh",
        "givenNames": "Iftikhar",
        "otherNames": "Ifti",
        "middleName": null,
        "maidenName": null,
        "pids": "139",
        "mid": null,
        "fid": null,
        "gender": "male",
        "born": null,
        "img": "../assets/img/person/144.jpg",
        "sibOrder": null,
        "verifications": "135"
    },
    {
        "id": "145",
        "surName": "Rahman",
        "givenNames": "Ariyan",
        "otherNames": null,
        "middleName": "Mohsin",
        "maidenName": null,
        "pids": null,
        "mid": "37",
        "fid": "42",
        "gender": "male",
        "born": "2017-12-19",
        "img": "../assets/img/person/145.jpg",
        "sibOrder": "a",
        "verifications": null
    },
    {
        "id": "146",
        "surName": "Khan",
        "givenNames": "Safiyya",
        "otherNames": null,
        "middleName": null,
        "maidenName": null,
        "pids": null,
        "mid": "56",
        "fid": "53",
        "gender": "female",
        "born": null,
        "img": "../assets/img/person/146.jpg",
        "sibOrder": "b",
        "verifications": null
    },
    {
        "id": "147",
        "surName": "?",
        "givenNames": "?",
        "otherNames": null,
        "middleName": null,
        "maidenName": null,
        "pids": "61",
        "mid": null,
        "fid": null,
        "gender": "male",
        "born": null,
        "img": "../assets/img/person/147.jpg",
        "sibOrder": null,
        "verifications": null
    },
    {
        "id": "148",
        "surName": "?",
        "givenNames": "?",
        "otherNames": null,
        "middleName": null,
        "maidenName": null,
        "pids": null,
        "mid": "96",
        "fid": "95",
        "gender": "male",
        "born": null,
        "img": "../assets/img/person/148.jpg",
        "sibOrder": "e",
        "verifications": null
    },
    {
        "id": "149",
        "surName": "?",
        "givenNames": "?",
        "otherNames": null,
        "middleName": null,
        "maidenName": null,
        "pids": null,
        "mid": "96",
        "fid": "95",
        "gender": "male",
        "born": null,
        "img": "../assets/img/person/149.jpg",
        "sibOrder": "g",
        "verifications": null
    },
    {
        "id": "150",
        "surName": "Uddin",
        "givenNames": "Razzak",
        "otherNames": null,
        "middleName": null,
        "maidenName": null,
        "pids": "162",
        "mid": "97",
        "fid": "104",
        "gender": "male",
        "born": null,
        "img": "../assets/img/person/150.jpg",
        "sibOrder": "a",
        "verifications": null
    },
    {
        "id": "151",
        "surName": "Uddin",
        "givenNames": "Rizaoul Karim",
        "otherNames": null,
        "middleName": null,
        "maidenName": null,
        "pids": "163",
        "mid": "97",
        "fid": "104",
        "gender": "male",
        "born": null,
        "img": "../assets/img/person/151.jpg",
        "sibOrder": "b",
        "verifications": null
    },
    {
        "id": "152",
        "surName": "?",
        "givenNames": "Naseema",
        "otherNames": null,
        "middleName": null,
        "maidenName": "Uddin",
        "pids": "164",
        "mid": "97",
        "fid": "104",
        "gender": "female",
        "born": null,
        "img": "../assets/img/person/152.jpg",
        "sibOrder": "c",
        "verifications": null
    },
    {
        "id": "153",
        "surName": "Tarafder",
        "givenNames": "Shafiqul",
        "otherNames": null,
        "middleName": null,
        "maidenName": null,
        "pids": "165",
        "mid": "97",
        "fid": "104",
        "gender": "male",
        "born": null,
        "img": "../assets/img/person/153.jpg",
        "sibOrder": "d",
        "verifications": null
    },
    {
        "id": "154",
        "surName": "Uddin",
        "givenNames": "Rafiqul",
        "otherNames": null,
        "middleName": null,
        "maidenName": null,
        "pids": "166",
        "mid": "97",
        "fid": "104",
        "gender": "male",
        "born": null,
        "img": "../assets/img/person/154.jpg",
        "sibOrder": "e",
        "verifications": null
    },
    {
        "id": "155",
        "surName": "?",
        "givenNames": "Shahanaj",
        "otherNames": null,
        "middleName": null,
        "maidenName": "Uddin",
        "pids": "167",
        "mid": "97",
        "fid": "104",
        "gender": "female",
        "born": null,
        "img": "../assets/img/person/155.jpg",
        "sibOrder": "f",
        "verifications": null
    },
    {
        "id": "156",
        "surName": "?",
        "givenNames": "Shazida",
        "otherNames": null,
        "middleName": null,
        "maidenName": "Uddin",
        "pids": "168",
        "mid": "97",
        "fid": "104",
        "gender": "female",
        "born": null,
        "img": "../assets/img/person/156.jpg",
        "sibOrder": "g",
        "verifications": null
    },
    {
        "id": "157",
        "surName": "?",
        "givenNames": "Mazida",
        "otherNames": null,
        "middleName": null,
        "maidenName": "Uddin",
        "pids": "169",
        "mid": "97",
        "fid": "104",
        "gender": "female",
        "born": null,
        "img": "../assets/img/person/157.jpg",
        "sibOrder": "h",
        "verifications": null
    },
    {
        "id": "158",
        "surName": "Uddin",
        "givenNames": "Momin",
        "otherNames": null,
        "middleName": null,
        "maidenName": null,
        "pids": "170",
        "mid": "97",
        "fid": "104",
        "gender": "male",
        "born": null,
        "img": "../assets/img/person/158.jpg",
        "sibOrder": "i",
        "verifications": null
    },
    {
        "id": "159",
        "surName": "Uddin",
        "givenNames": "Amin",
        "otherNames": null,
        "middleName": null,
        "maidenName": null,
        "pids": "171",
        "mid": "97",
        "fid": "104",
        "gender": "male",
        "born": null,
        "img": "../assets/img/person/159.jpg",
        "sibOrder": "j",
        "verifications": null
    },
    {
        "id": "160",
        "surName": "?",
        "givenNames": "Rashida",
        "otherNames": null,
        "middleName": null,
        "maidenName": "Uddin",
        "pids": "172",
        "mid": "97",
        "fid": "104",
        "gender": "female",
        "born": null,
        "img": "../assets/img/person/160.jpg",
        "sibOrder": "k",
        "verifications": null
    },
    {
        "id": "161",
        "surName": "Uddin",
        "givenNames": "Alamin",
        "otherNames": null,
        "middleName": null,
        "maidenName": null,
        "pids": "173",
        "mid": "97",
        "fid": "104",
        "gender": "male",
        "born": null,
        "img": "../assets/img/person/161.jpg",
        "sibOrder": "l",
        "verifications": null
    },
    {
        "id": "162",
        "surName": "?",
        "givenNames": "?",
        "otherNames": null,
        "middleName": null,
        "maidenName": null,
        "pids": "150",
        "mid": null,
        "fid": null,
        "gender": "female",
        "born": null,
        "img": "../assets/img/person/162.jpg",
        "sibOrder": null,
        "verifications": null
    },
    {
        "id": "163",
        "surName": "?",
        "givenNames": "?",
        "otherNames": null,
        "middleName": null,
        "maidenName": null,
        "pids": "151",
        "mid": null,
        "fid": null,
        "gender": "female",
        "born": null,
        "img": "../assets/img/person/163.jpg",
        "sibOrder": null,
        "verifications": null
    },
    {
        "id": "164",
        "surName": "?",
        "givenNames": "?",
        "otherNames": null,
        "middleName": null,
        "maidenName": null,
        "pids": "152",
        "mid": null,
        "fid": null,
        "gender": "male",
        "born": null,
        "img": "../assets/img/person/164.jpg",
        "sibOrder": null,
        "verifications": null
    },
    {
        "id": "165",
        "surName": "Tarafder",
        "givenNames": "Farhana",
        "otherNames": "Moni",
        "middleName": null,
        "maidenName": null,
        "pids": "153",
        "mid": null,
        "fid": null,
        "gender": "female",
        "born": null,
        "img": "../assets/img/person/165.jpg",
        "sibOrder": null,
        "verifications": null
    },
    {
        "id": "166",
        "surName": "?",
        "givenNames": "?",
        "otherNames": null,
        "middleName": null,
        "maidenName": null,
        "pids": "154",
        "mid": null,
        "fid": null,
        "gender": "female",
        "born": null,
        "img": "../assets/img/person/166.jpg",
        "sibOrder": null,
        "verifications": null
    },
    {
        "id": "167",
        "surName": "?",
        "givenNames": "?",
        "otherNames": null,
        "middleName": null,
        "maidenName": null,
        "pids": "155",
        "mid": null,
        "fid": null,
        "gender": "male",
        "born": null,
        "img": "../assets/img/person/167.jpg",
        "sibOrder": null,
        "verifications": null
    },
    {
        "id": "168",
        "surName": "?",
        "givenNames": "?",
        "otherNames": null,
        "middleName": null,
        "maidenName": null,
        "pids": "156",
        "mid": null,
        "fid": null,
        "gender": "male",
        "born": null,
        "img": "../assets/img/person/168.jpg",
        "sibOrder": null,
        "verifications": null
    },
    {
        "id": "169",
        "surName": "?",
        "givenNames": "?",
        "otherNames": null,
        "middleName": null,
        "maidenName": null,
        "pids": "157",
        "mid": null,
        "fid": null,
        "gender": "male",
        "born": null,
        "img": "../assets/img/person/169.jpg",
        "sibOrder": null,
        "verifications": null
    },
    {
        "id": "170",
        "surName": "?",
        "givenNames": "?",
        "otherNames": null,
        "middleName": null,
        "maidenName": null,
        "pids": "158",
        "mid": null,
        "fid": null,
        "gender": "female",
        "born": null,
        "img": "../assets/img/person/170.jpg",
        "sibOrder": null,
        "verifications": null
    },
    {
        "id": "171",
        "surName": "?",
        "givenNames": "?",
        "otherNames": null,
        "middleName": null,
        "maidenName": null,
        "pids": "159",
        "mid": null,
        "fid": null,
        "gender": "female",
        "born": null,
        "img": "../assets/img/person/171.jpg",
        "sibOrder": null,
        "verifications": null
    },
    {
        "id": "172",
        "surName": "?",
        "givenNames": "?",
        "otherNames": null,
        "middleName": null,
        "maidenName": null,
        "pids": "160",
        "mid": null,
        "fid": null,
        "gender": "male",
        "born": null,
        "img": "../assets/img/person/172.jpg",
        "sibOrder": null,
        "verifications": null
    },
    {
        "id": "173",
        "surName": "?",
        "givenNames": "?",
        "otherNames": null,
        "middleName": null,
        "maidenName": null,
        "pids": "161",
        "mid": null,
        "fid": null,
        "gender": "female",
        "born": null,
        "img": "../assets/img/person/173.jpg",
        "sibOrder": null,
        "verifications": null
    },
    {
        "id": "174",
        "surName": "Fahad",
        "givenNames": "Jubair",
        "otherNames": null,
        "middleName": null,
        "maidenName": null,
        "pids": null,
        "mid": "153",
        "fid": "165",
        "gender": "male",
        "born": null,
        "img": null,
        "sibOrder": "a",
        "verifications": null
    },
    {
        "id": "175",
        "surName": null,
        "givenNames": "Taqwa",
        "otherNames": null,
        "middleName": null,
        "maidenName": null,
        "pids": null,
        "mid": "153",
        "fid": "165",
        "gender": "female",
        "born": null,
        "img": null,
        "sibOrder": "b",
        "verifications": null
    }
]